{"nodes": [{"color": "#00ff7f", "id": "anaphylaxis", "size": 9, "label": "anaphylaxis", "x": 9, "y": 115}, {"color": "#00f", "id": "may because", "size": 9, "label": "may because", "x": 250, "y": 186}, {"color": "#f00", "id": "death", "size": 9, "label": "death", "x": 0, "y": -32}, {"color": "#f00", "id": "a serious allergic reaction", "size": 9, "label": "a serious allergic reaction", "x": 9, "y": 115}, {"color": "#00f", "id": "be", "size": 9, "label": "be", "x": 250, "y": 186}, {"color": "#f00", "id": "onset", "size": 9, "label": "onset", "x": 0, "y": -32}, {"color": "#f00", "id": "-PRON-", "size": 9, "label": "-PRON-", "x": 9, "y": 115}, {"color": "#00f", "id": "cause", "size": 9, "label": "cause", "x": 250, "y": 186}, {"color": "#f00", "id": "more than one", "size": 9, "label": "more than one", "x": 0, "y": -32}, {"color": "#f00", "id": "common cause", "size": 9, "label": "common cause", "x": 9, "y": 115}, {"color": "#00f", "id": "include", "size": 9, "label": "include", "x": 250, "y": 186}, {"color": "#f00", "id": "medication", "size": 9, "label": "medication", "x": 0, "y": -32}, {"color": "#f00", "id": "food", "size": 9, "label": "food", "x": 0, "y": -32}, {"color": "#f00", "id": "diagnosis", "size": 9, "label": "diagnosis", "x": 9, "y": 115}, {"color": "#00f", "id": "be base", "size": 9, "label": "be base", "x": 250, "y": 186}, {"color": "#f00", "id": "exposure", "size": 9, "label": "exposure", "x": 0, "y": -32}, {"color": "#f00", "id": "the primary treatment", "size": 9, "label": "the primary treatment", "x": 9, "y": 115}, {"color": "#f00", "id": "epinephrine injection", "size": 9, "label": "epinephrine injection", "x": 0, "y": -32}, {"color": "#f00", "id": "the person", "size": 9, "label": "the person", "x": 0, "y": -32}, {"color": "#f00", "id": "intravenous fluid", "size": 9, "label": "intravenous fluid", "x": 0, "y": -32}, {"color": "#f00", "id": "a muscle", "size": 9, "label": "a muscle", "x": 0, "y": -32}, {"color": "#f00", "id": "the condition", "size": 9, "label": "the condition", "x": 9, "y": 115}, {"color": "#00f", "id": "be recommend", "size": 9, "label": "be recommend", "x": 250, "y": 186}, {"color": "#f00", "id": "people", "size": 9, "label": "people", "x": 0, "y": -32}, {"color": "#f00", "id": "a history", "size": 9, "label": "a history", "x": 0, "y": -32}, {"color": "#f00", "id": "identification", "size": 9, "label": "identification", "x": 9, "y": 115}, {"color": "#f00", "id": "an epinephrine autoinjector", "size": 9, "label": "an epinephrine autoinjector", "x": 9, "y": 115}, {"color": "#f00", "id": "0.05 - 2 %", "size": 9, "label": "0.05 - 2 %", "x": 9, "y": 115}, {"color": "#00f", "id": "to experience", "size": 9, "label": "to experience", "x": 250, "y": 186}, {"color": "#f00", "id": "the population", "size": 9, "label": "the population", "x": 9, "y": 115}, {"color": "#00f", "id": "be estimate", "size": 9, "label": "be estimate", "x": 250, "y": 186}, {"color": "#f00", "id": "some point", "size": 9, "label": "some point", "x": 0, "y": -32}, {"color": "#f00", "id": "life", "size": 9, "label": "life", "x": 0, "y": -32}, {"color": "#00f", "id": "go", "size": 9, "label": "go", "x": 250, "y": 186}, {"color": "#f00", "id": "a hospital", "size": 9, "label": "a hospital", "x": 0, "y": -32}, {"color": "#f00", "id": "the united states", "size": 9, "label": "the united states", "x": 0, "y": -32}, {"color": "#f00", "id": "the term", "size": 9, "label": "the term", "x": 9, "y": 115}, {"color": "#00f", "id": "come", "size": 9, "label": "come", "x": 250, "y": 186}, {"color": "#f00", "id": "\"from the ", "size": 9, "label": "\"from the ", "x": 0, "y": -32}, {"color": "#f00", "id": "intravenous", "size": 9, "label": "intravenous", "x": 0, "y": -32}, {"color": "#00f", "id": "typically present", "size": 9, "label": "typically present", "x": 250, "y": 186}, {"color": "#f00", "id": "minute or hour", "size": 9, "label": "minute or hour", "x": 0, "y": -32}, {"color": "#f00", "id": "minute", "size": 9, "label": "minute", "x": 0, "y": -32}, {"color": "#f00", "id": "hour", "size": 9, "label": "hour", "x": 0, "y": -32}, {"color": "#f00", "id": "many different symptom", "size": 9, "label": "many different symptom", "x": 0, "y": -32}, {"color": "#f00", "id": "symptom", "size": 9, "label": "symptom", "x": 9, "y": 115}, {"color": "#00f", "id": "typically include", "size": 9, "label": "typically include", "x": 250, "y": 186}, {"color": "#f00", "id": "generalized hive", "size": 9, "label": "generalized hive", "x": 0, "y": -32}, {"color": "#f00", "id": "itchiness", "size": 9, "label": "itchiness", "x": 0, "y": -32}, {"color": "#f00", "id": "flushing", "size": 9, "label": "flushing", "x": 0, "y": -32}, {"color": "#f00", "id": "angioedema", "size": 9, "label": "angioedema", "x": 0, "y": -32}, {"color": "#f00", "id": "the afflict tissue", "size": 9, "label": "the afflict tissue", "x": 0, "y": -32}, {"color": "#00f", "id": "may describe", "size": 9, "label": "may describe", "x": 250, "y": 186}, {"color": "#f00", "id": "underlie coronary disease", "size": 9, "label": "underlie coronary disease", "x": 9, "y": 115}, {"color": "#f00", "id": "great risk", "size": 9, "label": "great risk", "x": 0, "y": -32}, {"color": "#f00", "id": "cardiac effect", "size": 9, "label": "cardiac effect", "x": 0, "y": -32}, {"color": "#f00", "id": "rarely very low blood pressure", "size": 9, "label": "rarely very low blood pressure", "x": 9, "y": 115}, {"color": "#00f", "id": "may be", "size": 9, "label": "may be", "x": 250, "y": 186}, {"color": "#f00", "id": "the only sign", "size": 9, "label": "the only sign", "x": 0, "y": -32}, {"color": "#00f", "id": "can occur", "size": 9, "label": "can occur", "x": 250, "y": 186}, {"color": "#f00", "id": "almost any foreign substance", "size": 9, "label": "almost any foreign substance", "x": 0, "y": -32}, {"color": "#f00", "id": "response", "size": 9, "label": "response", "x": 0, "y": -32}, {"color": "#f00", "id": "common trigger", "size": 9, "label": "common trigger", "x": 9, "y": 115}, {"color": "#f00", "id": "old adult", "size": 9, "label": "old adult", "x": 0, "y": -32}, {"color": "#f00", "id": "child", "size": 9, "label": "child", "x": 0, "y": -32}, {"color": "#f00", "id": "hpv", "size": 9, "label": "hpv", "x": 9, "y": 115}, {"color": "#f00", "id": "six vaccine", "size": 9, "label": "six vaccine", "x": 9, "y": 115}, {"color": "#00f", "id": "be recognize", "size": 9, "label": "be recognize", "x": 250, "y": 186}, {"color": "#f00", "id": "a because", "size": 9, "label": "a because", "x": 0, "y": -32}, {"color": "#f00", "id": "six", "size": 9, "label": "six", "x": 9, "y": 115}, {"color": "#f00", "id": "many food", "size": 9, "label": "many food", "x": 9, "y": 115}, {"color": "#00f", "id": "can trigger", "size": 9, "label": "can trigger", "x": 250, "y": 186}, {"color": "#f00", "id": "the first know ingestion", "size": 9, "label": "the first know ingestion", "x": 0, "y": -32}, {"color": "#f00", "id": "first", "size": 9, "label": "first", "x": 0, "y": -32}, {"color": "#f00", "id": "the most prevalent cause", "size": 9, "label": "the most prevalent cause", "x": 0, "y": -32}, {"color": "#f00", "id": "chickpea", "size": 9, "label": "chickpea", "x": 9, "y": 115}, {"color": "#00f", "id": "be encounter", "size": 9, "label": "be encounter", "x": 250, "y": 186}, {"color": "#f00", "id": "source", "size": 9, "label": "source", "x": 0, "y": -32}, {"color": "#f00", "id": "asia", "size": 9, "label": "asia", "x": 0, "y": -32}, {"color": "#f00", "id": "rice", "size": 9, "label": "rice", "x": 9, "y": 115}, {"color": "#f00", "id": "severe case", "size": 9, "label": "severe case", "x": 9, "y": 115}, {"color": "#00f", "id": "be cause", "size": 9, "label": "be cause", "x": 250, "y": 186}, {"color": "#f00", "id": "the allergen", "size": 9, "label": "the allergen", "x": 0, "y": -32}, {"color": "#f00", "id": "80 %", "size": 9, "label": "80 %", "x": 9, "y": 115}, {"color": "#00f", "id": "isolate", "size": 9, "label": "isolate", "x": 250, "y": 186}, {"color": "#f00", "id": "any medication", "size": 9, "label": "any medication", "x": 9, "y": 115}, {"color": "#00f", "id": "may potentially trigger", "size": 9, "label": "may potentially trigger", "x": 250, "y": 186}, {"color": "#f00", "id": "some medication", "size": 9, "label": "some medication", "x": 9, "y": 115}, {"color": "#00f", "id": "because", "size": 9, "label": "because", "x": 250, "y": 186}, {"color": "#00f", "id": "occur", "size": 9, "label": "occur", "x": 250, "y": 186}, {"color": "#f00", "id": "treatment", "size": 9, "label": "treatment", "x": 0, "y": -32}, {"color": "#f00", "id": "few than one", "size": 9, "label": "few than one", "x": 0, "y": -32}, {"color": "#f00", "id": "\"50", "size": 9, "label": "\"50", "x": 0, "y": -32}, {"color": "#f00", "id": "\"every 50", "size": 9, "label": "\"every 50", "x": 0, "y": -32}, {"color": "#f00", "id": "\"every 2", "size": 9, "label": "\"every 2", "x": 0, "y": -32}, {"color": "#f00", "id": "penicillin", "size": 9, "label": "penicillin", "x": 9, "y": 115}, {"color": "#f00", "id": "wasp", "size": 9, "label": "wasp", "x": 9, "y": 115}, {"color": "#f00", "id": "susceptible people", "size": 9, "label": "susceptible people", "x": 0, "y": -32}, {"color": "#f00", "id": "bee", "size": 9, "label": "bee", "x": 9, "y": 115}, {"color": "#f00", "id": "ant", "size": 9, "label": "ant", "x": 9, "y": 115}, {"color": "#f00", "id": "triatominae", "size": 9, "label": "triatominae", "x": 9, "y": 115}, {"color": "#f00", "id": "asthma", "size": 9, "label": "asthma", "x": 9, "y": 115}, {"color": "#f00", "id": "latex", "size": 9, "label": "latex", "x": 0, "y": -32}, {"color": "#f00", "id": "high risk", "size": 9, "label": "high risk", "x": 0, "y": -32}, {"color": "#f00", "id": "atopic disease", "size": 9, "label": "atopic disease", "x": 9, "y": 115}, {"color": "#f00", "id": "eczema", "size": 9, "label": "eczema", "x": 9, "y": 115}, {"color": "#f00", "id": "allergic rhinitis", "size": 9, "label": "allergic rhinitis", "x": 9, "y": 115}, {"color": "#f00", "id": "more than 90 %", "size": 9, "label": "more than 90 %", "x": 9, "y": 115}, {"color": "#00f", "id": "have", "size": 9, "label": "have", "x": 250, "y": 186}, {"color": "#00f", "id": "find", "size": 9, "label": "find", "x": 250, "y": 186}, {"color": "#f00", "id": "rapid onset", "size": 9, "label": "rapid onset", "x": 9, "y": 115}, {"color": "#00f", "id": "affect", "size": 9, "label": "affect", "x": 250, "y": 186}, {"color": "#f00", "id": "many body system", "size": 9, "label": "many body system", "x": 0, "y": -32}, {"color": "#f00", "id": "a severe allergic reaction", "size": 9, "label": "a severe allergic reaction", "x": 0, "y": -32}, {"color": "#00f", "id": "be diagnose", "size": 9, "label": "be diagnose", "x": 250, "y": 186}, {"color": "#f00", "id": "the basis", "size": 9, "label": "the basis", "x": 0, "y": -32}, {"color": "#f00", "id": "a person 's sign\"]", "size": 9, "label": "a person 's sign\"]", "x": 0, "y": -32}, {"color": "#f00", "id": "a normal blood pressure", "size": 9, "label": "a normal blood pressure", "x": 0, "y": -32}, {"color": "#f00", "id": "biphasic anaphylaxis", "size": 9, "label": "biphasic anaphylaxis", "x": 9, "y": 115}, {"color": "#f00", "id": "pseudoanaphylaxis or anaphylactoid reaction", "size": 9, "label": "pseudoanaphylaxis or anaphylactoid reaction", "x": 9, "y": 115}, {"color": "#00f", "id": "be a type of", "size": 9, "label": "be a type of", "x": 250, "y": 186}, {"color": "#00f", "id": "do not involve", "size": 9, "label": "do not involve", "x": 250, "y": 186}, {"color": "#f00", "id": "an allergic reaction", "size": 9, "label": "an allergic reaction", "x": 0, "y": -32}, {"color": "#f00", "id": "a type", "size": 9, "label": "a type", "x": 9, "y": 115}, {"color": "#00f", "id": "can only be determine", "size": 9, "label": "can only be determine", "x": 250, "y": 186}, {"color": "#f00", "id": "history", "size": 9, "label": "history", "x": 0, "y": -32}, {"color": "#f00", "id": "skin", "size": 9, "label": "skin", "x": 0, "y": -32}, {"color": "#f00", "id": "testing", "size": 9, "label": "testing", "x": 0, "y": -32}, {"color": "#f00", "id": "blood", "size": 9, "label": "blood", "x": 0, "y": -32}, {"color": "#f00", "id": "question", "size": 9, "label": "question", "x": 0, "y": -32}, {"color": "#f00", "id": "non - immune form", "size": 9, "label": "non - immune form", "x": 9, "y": 115}, {"color": "#00f", "id": "typically do not entail", "size": 9, "label": "typically do not entail", "x": 250, "y": 186}, {"color": "#f00", "id": "itching or gastrointestinal symptom", "size": 9, "label": "itching or gastrointestinal symptom", "x": 0, "y": -32}, {"color": "#f00", "id": "a person", "size": 9, "label": "a person", "x": 9, "y": 115}, {"color": "#00f", "id": "die", "size": 9, "label": "die", "x": 250, "y": 186}, {"color": "#f00", "id": "immunotherapy", "size": 9, "label": "immunotherapy", "x": 9, "y": 115}, {"color": "#f00", "id": "98 %", "size": 9, "label": "98 %", "x": 0, "y": -32}, {"color": "#f00", "id": "80 - 90 %", "size": 9, "label": "80 - 90 %", "x": 0, "y": -32}, {"color": "#008000", "id": "allergy", "size": 9, "label": "allergy", "x": 0, "y": -32}, {"color": "#f00", "id": "fire ant", "size": 9, "label": "fire ant", "x": 0, "y": -32}, {"color": "#f00", "id": "hymenoptera", "size": 9, "label": "hymenoptera", "x": 9, "y": 115}, {"color": "#f00", "id": "hymenoptera venom", "size": 9, "label": "hymenoptera venom", "x": 9, "y": 115}, {"color": "#f00", "id": "yellowjacket", "size": 9, "label": "yellowjacket", "x": 0, "y": -32}, {"color": "#f00", "id": "hornet", "size": 9, "label": "hornet", "x": 0, "y": -32}, {"color": "#f00", "id": "adult", "size": 9, "label": "adult", "x": 0, "y": -32}, {"color": "#f00", "id": "most people", "size": 9, "label": "most people", "x": 9, "y": 115}, {"color": "#00f", "id": "simply avoid", "size": 9, "label": "simply avoid", "x": 250, "y": 186}, {"color": "#00f", "id": "be advise", "size": 9, "label": "be advise", "x": 250, "y": 186}, {"color": "#f00", "id": "a medical emergency", "size": 9, "label": "a medical emergency", "x": 9, "y": 115}, {"color": "#00f", "id": "may require", "size": 9, "label": "may require", "x": 250, "y": 186}, {"color": "#f00", "id": "resuscitation measure", "size": 9, "label": "resuscitation measure", "x": 0, "y": -32}, {"color": "#f00", "id": "close monitoring", "size": 9, "label": "close monitoring", "x": 0, "y": -32}, {"color": "#f00", "id": "large volume", "size": 9, "label": "large volume", "x": 0, "y": -32}, {"color": "#f00", "id": "supplemental oxygen", "size": 9, "label": "supplemental oxygen", "x": 0, "y": -32}, {"color": "#f00", "id": "airway management", "size": 9, "label": "airway management", "x": 0, "y": -32}, {"color": "#f00", "id": "the treatment", "size": 9, "label": "the treatment", "x": 9, "y": 115}, {"color": "#00f", "id": "use", "size": 9, "label": "use", "x": 250, "y": 186}, {"color": "#f00", "id": "adjunct", "size": 9, "label": "adjunct", "x": 0, "y": -32}, {"color": "#f00", "id": "steroid", "size": 9, "label": "steroid", "x": 9, "y": 115}, {"color": "#f00", "id": "choice", "size": 9, "label": "choice", "x": 9, "y": 115}, {"color": "#f00", "id": "epinephrine", "size": 9, "label": "epinephrine", "x": 9, "y": 115}, {"color": "#f00", "id": "example", "size": 9, "label": "example", "x": 0, "y": -32}, {"color": "#f00", "id": "antihistamine", "size": 9, "label": "antihistamine", "x": 9, "y": 115}, {"color": "#f00", "id": "dexamethasone", "size": 9, "label": "dexamethasone", "x": 0, "y": -32}, {"color": "#f00", "id": "a period", "size": 9, "label": "a period", "x": 9, "y": 115}, {"color": "#f00", "id": "hospital", "size": 9, "label": "hospital", "x": 9, "y": 115}, {"color": "#f00", "id": "24 hour", "size": 9, "label": "24 hour", "x": 9, "y": 115}, {"color": "#f00", "id": "between 2", "size": 9, "label": "between 2", "x": 9, "y": 115}, {"color": "#f00", "id": "no absolute contraindication", "size": 9, "label": "no absolute contraindication", "x": 0, "y": -32}, {"color": "#f00", "id": "-PRON- use", "size": 9, "label": "-PRON- use", "x": 0, "y": -32}, {"color": "#f00", "id": "palpitation", "size": 9, "label": "palpitation", "x": 0, "y": -32}, {"color": "#f00", "id": "headache", "size": 9, "label": "headache", "x": 0, "y": -32}, {"color": "#f00", "id": "anxiety", "size": 9, "label": "anxiety", "x": 0, "y": -32}, {"color": "#f00", "id": "tremor", "size": 9, "label": "tremor", "x": 0, "y": -32}, {"color": "#f00", "id": "the effect", "size": 9, "label": "the effect", "x": 0, "y": -32}, {"color": "#f00", "id": "\u03b2-blocker", "size": 9, "label": "\u03b2-blocker", "x": 9, "y": 115}, {"color": "#00f", "id": "be not", "size": 9, "label": "be not", "x": 250, "y": 186}, {"color": "#f00", "id": "effective", "size": 9, "label": "effective", "x": 0, "y": -32}, {"color": "#00f", "id": "weigh", "size": 9, "label": "weigh", "x": 250, "y": 186}, {"color": "#f00", "id": "corticosteroid", "size": 9, "label": "corticosteroid", "x": 9, "y": 115}, {"color": "#00f", "id": "may be use", "size": 9, "label": "may be use", "x": 250, "y": 186}, {"color": "#f00", "id": "the risk", "size": 9, "label": "the risk", "x": 0, "y": -32}, {"color": "#f00", "id": "the hope", "size": 9, "label": "the hope", "x": 0, "y": -32}, {"color": "#00f", "id": "to make", "size": 9, "label": "to make", "x": 250, "y": 186}, {"color": "#f00", "id": "the current episode", "size": 9, "label": "the current episode", "x": 0, "y": -32}, {"color": "#f00", "id": "a difference", "size": 9, "label": "a difference", "x": 0, "y": -32}, {"color": "#00f", "id": "to have", "size": 9, "label": "to have", "x": 250, "y": 186}, {"color": "#f00", "id": "\"an \"\" allergy action plan\"", "size": 9, "label": "\"an \"\" allergy action plan\"", "x": 0, "y": -32}, {"color": "#f00", "id": "certain trigger", "size": 9, "label": "certain trigger", "x": 0, "y": -32}, {"color": "#f00", "id": "oral desensitization", "size": 9, "label": "oral desensitization", "x": 9, "y": 115}, {"color": "#f00", "id": "case", "size": 9, "label": "case", "x": 9, "y": 115}, {"color": "#00f", "id": "get", "size": 9, "label": "get", "x": 250, "y": 186}, {"color": "#f00", "id": "old", "size": 9, "label": "old", "x": 0, "y": -32}, {"color": "#00f", "id": "have a lifetime risk of", "size": 9, "label": "have a lifetime risk of", "x": 250, "y": 186}, {"color": "#f00", "id": "0.05 -2 %", "size": 9, "label": "0.05 -2 %", "x": 0, "y": -32}, {"color": "#f00", "id": "the number", "size": 9, "label": "the number", "x": 9, "y": 115}, {"color": "#f00", "id": "who", "size": 9, "label": "who", "x": 9, "y": 115}, {"color": "#f00", "id": "4", "size": 9, "label": "4", "x": 0, "y": -32}, {"color": "#f00", "id": "year", "size": 9, "label": "year", "x": 0, "y": -32}, {"color": "#f00", "id": "100000", "size": 9, "label": "100000", "x": 0, "y": -32}, {"color": "#f00", "id": "100000 person", "size": 9, "label": "100000 person", "x": 0, "y": -32}, {"color": "#f00", "id": "4 - 100", "size": 9, "label": "4 - 100", "x": 0, "y": -32}, {"color": "#f00", "id": "\"4 - 100 per 100", "size": 9, "label": "\"4 - 100 per 100", "x": 0, "y": -32}, {"color": "#f00", "id": "more than one attack", "size": 9, "label": "more than one attack", "x": 0, "y": -32}, {"color": "#f00", "id": "the 1980s", "size": 9, "label": "the 1980s", "x": 9, "y": 115}, {"color": "#00f", "id": "lead", "size": 9, "label": "lead", "x": 250, "y": 186}, {"color": "#f00", "id": "000", "size": 9, "label": "000", "x": 0, "y": -32}, {"color": "#f00", "id": "2.4", "size": 9, "label": "2.4", "x": 0, "y": -32}, {"color": "#f00", "id": "\"500 - 1 ", "size": 9, "label": "\"500 - 1 ", "x": 0, "y": -32}, {"color": "#f00", "id": "15 death", "size": 9, "label": "15 death", "x": 0, "y": -32}, {"color": "#f00", "id": "500", "size": 9, "label": "500", "x": 0, "y": -32}, {"color": "#f00", "id": "australia", "size": 9, "label": "australia", "x": 0, "y": -32}, {"color": "#f00", "id": "15", "size": 9, "label": "15", "x": 0, "y": -32}, {"color": "#00f", "id": "primarily occur", "size": 9, "label": "primarily occur", "x": 250, "y": 186}, {"color": "#f00", "id": "male", "size": 9, "label": "male", "x": 0, "y": -32}, {"color": "#00f", "id": "be most commonly trigger", "size": 9, "label": "be most commonly trigger", "x": 250, "y": 186}, {"color": "#00f", "id": "change", "size": 9, "label": "change", "x": 250, "y": 186}, {"color": "#f00", "id": "speech", "size": 9, "label": "speech", "x": 0, "y": -32}, {"color": "#f00", "id": "-PRON- nice quality", "size": 9, "label": "-PRON- nice quality", "x": 0, "y": -32}], "edges": [{"color": "#aaa", "id": "e1", "size": 0.1, "source": "anaphylaxis", "target": "may because"}, {"color": "#aaa", "id": "e2", "size": 0.1, "source": "death", "target": "may because"}, {"color": "#aaa", "id": "e3", "size": 0.1, "source": "a serious allergic reaction", "target": "be"}, {"color": "#aaa", "id": "e4", "size": 0.1, "source": "onset", "target": "be"}, {"color": "#aaa", "id": "e5", "size": 0.1, "source": "anaphylaxis", "target": "be"}, {"color": "#aaa", "id": "e6", "size": 0.1, "source": "-PRON-", "target": "cause"}, {"color": "#aaa", "id": "e7", "size": 0.1, "source": "more than one", "target": "cause"}, {"color": "#aaa", "id": "e8", "size": 0.1, "source": "common cause", "target": "include"}, {"color": "#aaa", "id": "e9", "size": 0.1, "source": "medication", "target": "include"}, {"color": "#aaa", "id": "e10", "size": 0.1, "source": "food", "target": "include"}, {"color": "#aaa", "id": "e11", "size": 0.1, "source": "diagnosis", "target": "be base"}, {"color": "#aaa", "id": "e12", "size": 0.1, "source": "exposure", "target": "be base"}, {"color": "#aaa", "id": "e13", "size": 0.1, "source": "the primary treatment", "target": "be"}, {"color": "#aaa", "id": "e14", "size": 0.1, "source": "epinephrine injection", "target": "be"}, {"color": "#aaa", "id": "e15", "size": 0.1, "source": "the person", "target": "be"}, {"color": "#aaa", "id": "e16", "size": 0.1, "source": "intravenous fluid", "target": "be"}, {"color": "#aaa", "id": "e17", "size": 0.1, "source": "a muscle", "target": "be"}, {"color": "#aaa", "id": "e18", "size": 0.1, "source": "the condition", "target": "be recommend"}, {"color": "#aaa", "id": "e19", "size": 0.1, "source": "people", "target": "be recommend"}, {"color": "#aaa", "id": "e20", "size": 0.1, "source": "anaphylaxis", "target": "be recommend"}, {"color": "#aaa", "id": "e21", "size": 0.1, "source": "a history", "target": "be recommend"}, {"color": "#aaa", "id": "e22", "size": 0.1, "source": "identification", "target": "be recommend"}, {"color": "#aaa", "id": "e23", "size": 0.1, "source": "an epinephrine autoinjector", "target": "be recommend"}, {"color": "#aaa", "id": "e24", "size": 0.1, "source": "0.05 - 2 %", "target": "to experience"}, {"color": "#aaa", "id": "e25", "size": 0.1, "source": "anaphylaxis", "target": "to experience"}, {"color": "#aaa", "id": "e26", "size": 0.1, "source": "the population", "target": "to experience"}, {"color": "#aaa", "id": "e27", "size": 0.1, "source": "0.05 - 2 %", "target": "be estimate"}, {"color": "#aaa", "id": "e28", "size": 0.1, "source": "anaphylaxis", "target": "be estimate"}, {"color": "#aaa", "id": "e29", "size": 0.1, "source": "some point", "target": "be estimate"}, {"color": "#aaa", "id": "e30", "size": 0.1, "source": "life", "target": "be estimate"}, {"color": "#aaa", "id": "e31", "size": 0.1, "source": "the population", "target": "be estimate"}, {"color": "#aaa", "id": "e32", "size": 0.1, "source": "people", "target": "go"}, {"color": "#aaa", "id": "e33", "size": 0.1, "source": "anaphylaxis", "target": "go"}, {"color": "#aaa", "id": "e34", "size": 0.1, "source": "a hospital", "target": "go"}, {"color": "#aaa", "id": "e35", "size": 0.1, "source": "the united states", "target": "go"}, {"color": "#aaa", "id": "e36", "size": 0.1, "source": "the term", "target": "come"}, {"color": "#aaa", "id": "e37", "size": 0.1, "source": "\"from the ", "target": "come"}, {"color": "#aaa", "id": "e38", "size": 0.1, "source": "exposure", "target": "be"}, {"color": "#aaa", "id": "e39", "size": 0.1, "source": "intravenous", "target": "be"}, {"color": "#aaa", "id": "e40", "size": 0.1, "source": "anaphylaxis", "target": "typically present"}, {"color": "#aaa", "id": "e41", "size": 0.1, "source": "minute or hour", "target": "typically present"}, {"color": "#aaa", "id": "e42", "size": 0.1, "source": "minute", "target": "typically present"}, {"color": "#aaa", "id": "e43", "size": 0.1, "source": "hour", "target": "typically present"}, {"color": "#aaa", "id": "e44", "size": 0.1, "source": "many different symptom", "target": "typically present"}, {"color": "#aaa", "id": "e45", "size": 0.1, "source": "symptom", "target": "typically include"}, {"color": "#aaa", "id": "e46", "size": 0.1, "source": "generalized hive", "target": "typically include"}, {"color": "#aaa", "id": "e47", "size": 0.1, "source": "itchiness", "target": "typically include"}, {"color": "#aaa", "id": "e48", "size": 0.1, "source": "flushing", "target": "typically include"}, {"color": "#aaa", "id": "e49", "size": 0.1, "source": "angioedema", "target": "typically include"}, {"color": "#aaa", "id": "e50", "size": 0.1, "source": "the afflict tissue", "target": "typically include"}, {"color": "#aaa", "id": "e51", "size": 0.1, "source": "angioedema", "target": "may describe"}, {"color": "#aaa", "id": "e52", "size": 0.1, "source": "itchiness", "target": "may describe"}, {"color": "#aaa", "id": "e53", "size": 0.1, "source": "underlie coronary disease", "target": "be"}, {"color": "#aaa", "id": "e54", "size": 0.1, "source": "great risk", "target": "be"}, {"color": "#aaa", "id": "e55", "size": 0.1, "source": "cardiac effect", "target": "be"}, {"color": "#aaa", "id": "e56", "size": 0.1, "source": "rarely very low blood pressure", "target": "may be"}, {"color": "#aaa", "id": "e57", "size": 0.1, "source": "anaphylaxis", "target": "may be"}, {"color": "#aaa", "id": "e58", "size": 0.1, "source": "the only sign", "target": "may be"}, {"color": "#aaa", "id": "e59", "size": 0.1, "source": "anaphylaxis", "target": "can occur"}, {"color": "#aaa", "id": "e60", "size": 0.1, "source": "almost any foreign substance", "target": "can occur"}, {"color": "#aaa", "id": "e61", "size": 0.1, "source": "response", "target": "can occur"}, {"color": "#aaa", "id": "e62", "size": 0.1, "source": "common trigger", "target": "include"}, {"color": "#aaa", "id": "e63", "size": 0.1, "source": "medication", "target": "be"}, {"color": "#aaa", "id": "e64", "size": 0.1, "source": "old adult", "target": "be"}, {"color": "#aaa", "id": "e65", "size": 0.1, "source": "food", "target": "be"}, {"color": "#aaa", "id": "e66", "size": 0.1, "source": "child", "target": "be"}, {"color": "#aaa", "id": "e67", "size": 0.1, "source": "hpv", "target": "may because"}, {"color": "#aaa", "id": "e68", "size": 0.1, "source": "six vaccine", "target": "be recognize"}, {"color": "#aaa", "id": "e69", "size": 0.1, "source": "anaphylaxis", "target": "be recognize"}, {"color": "#aaa", "id": "e70", "size": 0.1, "source": "a because", "target": "be recognize"}, {"color": "#aaa", "id": "e71", "size": 0.1, "source": "six", "target": "be recognize"}, {"color": "#aaa", "id": "e72", "size": 0.1, "source": "many food", "target": "can trigger"}, {"color": "#aaa", "id": "e73", "size": 0.1, "source": "anaphylaxis", "target": "can trigger"}, {"color": "#aaa", "id": "e74", "size": 0.1, "source": "the first know ingestion", "target": "can trigger"}, {"color": "#aaa", "id": "e75", "size": 0.1, "source": "first", "target": "can trigger"}, {"color": "#aaa", "id": "e76", "size": 0.1, "source": "the most prevalent cause", "target": "be"}, {"color": "#aaa", "id": "e77", "size": 0.1, "source": "chickpea", "target": "be encounter"}, {"color": "#aaa", "id": "e78", "size": 0.1, "source": "anaphylaxis", "target": "be encounter"}, {"color": "#aaa", "id": "e79", "size": 0.1, "source": "source", "target": "be encounter"}, {"color": "#aaa", "id": "e80", "size": 0.1, "source": "asia", "target": "be encounter"}, {"color": "#aaa", "id": "e81", "size": 0.1, "source": "rice", "target": "be encounter"}, {"color": "#aaa", "id": "e82", "size": 0.1, "source": "severe case", "target": "be cause"}, {"color": "#aaa", "id": "e83", "size": 0.1, "source": "the allergen", "target": "be cause"}, {"color": "#aaa", "id": "e84", "size": 0.1, "source": "80 %", "target": "isolate"}, {"color": "#aaa", "id": "e85", "size": 0.1, "source": "anaphylaxis", "target": "isolate"}, {"color": "#aaa", "id": "e86", "size": 0.1, "source": "any medication", "target": "may potentially trigger"}, {"color": "#aaa", "id": "e87", "size": 0.1, "source": "anaphylaxis", "target": "may potentially trigger"}, {"color": "#aaa", "id": "e88", "size": 0.1, "source": "some medication", "target": "because"}, {"color": "#aaa", "id": "e89", "size": 0.1, "source": "anaphylaxis", "target": "because"}, {"color": "#aaa", "id": "e90", "size": 0.1, "source": "death", "target": "occur"}, {"color": "#aaa", "id": "e91", "size": 0.1, "source": "treatment", "target": "occur"}, {"color": "#aaa", "id": "e92", "size": 0.1, "source": "few than one", "target": "occur"}, {"color": "#aaa", "id": "e93", "size": 0.1, "source": "\"50", "target": "occur"}, {"color": "#aaa", "id": "e94", "size": 0.1, "source": "\"every 50", "target": "occur"}, {"color": "#aaa", "id": "e95", "size": 0.1, "source": "anaphylaxis", "target": "occur"}, {"color": "#aaa", "id": "e96", "size": 0.1, "source": "\"every 2", "target": "occur"}, {"color": "#aaa", "id": "e97", "size": 0.1, "source": "penicillin", "target": "occur"}, {"color": "#aaa", "id": "e98", "size": 0.1, "source": "wasp", "target": "may because"}, {"color": "#aaa", "id": "e99", "size": 0.1, "source": "susceptible people", "target": "may because"}, {"color": "#aaa", "id": "e100", "size": 0.1, "source": "bee", "target": "may because"}, {"color": "#aaa", "id": "e101", "size": 0.1, "source": "ant", "target": "may because"}, {"color": "#aaa", "id": "e102", "size": 0.1, "source": "triatominae", "target": "may because"}, {"color": "#aaa", "id": "e103", "size": 0.1, "source": "asthma", "target": "be"}, {"color": "#aaa", "id": "e104", "size": 0.1, "source": "latex", "target": "be"}, {"color": "#aaa", "id": "e105", "size": 0.1, "source": "high risk", "target": "be"}, {"color": "#aaa", "id": "e106", "size": 0.1, "source": "people", "target": "be"}, {"color": "#aaa", "id": "e107", "size": 0.1, "source": "atopic disease", "target": "be"}, {"color": "#aaa", "id": "e108", "size": 0.1, "source": "eczema", "target": "be"}, {"color": "#aaa", "id": "e109", "size": 0.1, "source": "allergic rhinitis", "target": "be"}, {"color": "#aaa", "id": "e110", "size": 0.1, "source": "more than 90 %", "target": "have"}, {"color": "#aaa", "id": "e111", "size": 0.1, "source": "asthma", "target": "have"}, {"color": "#aaa", "id": "e112", "size": 0.1, "source": "child", "target": "find"}, {"color": "#aaa", "id": "e113", "size": 0.1, "source": "a history", "target": "find"}, {"color": "#aaa", "id": "e114", "size": 0.1, "source": "rapid onset", "target": "affect"}, {"color": "#aaa", "id": "e115", "size": 0.1, "source": "many body system", "target": "affect"}, {"color": "#aaa", "id": "e116", "size": 0.1, "source": "rapid onset", "target": "be"}, {"color": "#aaa", "id": "e117", "size": 0.1, "source": "a severe allergic reaction", "target": "be"}, {"color": "#aaa", "id": "e118", "size": 0.1, "source": "anaphylaxis", "target": "be diagnose"}, {"color": "#aaa", "id": "e119", "size": 0.1, "source": "the basis", "target": "be diagnose"}, {"color": "#aaa", "id": "e120", "size": 0.1, "source": "symptom", "target": "be diagnose"}, {"color": "#aaa", "id": "e121", "size": 0.1, "source": "a person 's sign\"]", "target": "be diagnose"}, {"color": "#aaa", "id": "e122", "size": 0.1, "source": "the person", "target": "have"}, {"color": "#aaa", "id": "e123", "size": 0.1, "source": "a normal blood pressure", "target": "have"}, {"color": "#aaa", "id": "e124", "size": 0.1, "source": "biphasic anaphylaxis", "target": "be"}, {"color": "#aaa", "id": "e125", "size": 0.1, "source": "symptom", "target": "be"}, {"color": "#aaa", "id": "e126", "size": 0.1, "source": "the allergen", "target": "be"}, {"color": "#aaa", "id": "e127", "size": 0.1, "source": "pseudoanaphylaxis or anaphylactoid reaction", "target": "be a type of"}, {"color": "#aaa", "id": "e128", "size": 0.1, "source": "anaphylaxis", "target": "be a type of"}, {"color": "#aaa", "id": "e129", "size": 0.1, "source": "anaphylaxis", "target": "do not involve"}, {"color": "#aaa", "id": "e130", "size": 0.1, "source": "an allergic reaction", "target": "do not involve"}, {"color": "#aaa", "id": "e131", "size": 0.1, "source": "a type", "target": "do not involve"}, {"color": "#aaa", "id": "e132", "size": 0.1, "source": "pseudoanaphylaxis or anaphylactoid reaction", "target": "be"}, {"color": "#aaa", "id": "e133", "size": 0.1, "source": "an allergic reaction", "target": "be"}, {"color": "#aaa", "id": "e134", "size": 0.1, "source": "a type", "target": "be"}, {"color": "#aaa", "id": "e135", "size": 0.1, "source": "anaphylaxis", "target": "can only be determine"}, {"color": "#aaa", "id": "e136", "size": 0.1, "source": "history", "target": "can only be determine"}, {"color": "#aaa", "id": "e137", "size": 0.1, "source": "exposure", "target": "can only be determine"}, {"color": "#aaa", "id": "e138", "size": 0.1, "source": "skin", "target": "can only be determine"}, {"color": "#aaa", "id": "e139", "size": 0.1, "source": "the allergen", "target": "can only be determine"}, {"color": "#aaa", "id": "e140", "size": 0.1, "source": "testing", "target": "can only be determine"}, {"color": "#aaa", "id": "e141", "size": 0.1, "source": "blood", "target": "can only be determine"}, {"color": "#aaa", "id": "e142", "size": 0.1, "source": "question", "target": "can only be determine"}, {"color": "#aaa", "id": "e143", "size": 0.1, "source": "non - immune form", "target": "can only be determine"}, {"color": "#aaa", "id": "e144", "size": 0.1, "source": "asthma", "target": "typically do not entail"}, {"color": "#aaa", "id": "e145", "size": 0.1, "source": "itching or gastrointestinal symptom", "target": "typically do not entail"}, {"color": "#aaa", "id": "e146", "size": 0.1, "source": "a person", "target": "die"}, {"color": "#aaa", "id": "e147", "size": 0.1, "source": "anaphylaxis", "target": "die"}, {"color": "#aaa", "id": "e148", "size": 0.1, "source": "immunotherapy", "target": "be"}, {"color": "#aaa", "id": "e149", "size": 0.1, "source": "98 %", "target": "be"}, {"color": "#aaa", "id": "e150", "size": 0.1, "source": "80 - 90 %", "target": "be"}, {"color": "#aaa", "id": "e151", "size": 0.1, "source": "allergy", "target": "be"}, {"color": "#aaa", "id": "e152", "size": 0.1, "source": "fire ant", "target": "be"}, {"color": "#aaa", "id": "e153", "size": 0.1, "source": "hymenoptera", "target": "be"}, {"color": "#aaa", "id": "e154", "size": 0.1, "source": "hymenoptera venom", "target": "be"}, {"color": "#aaa", "id": "e155", "size": 0.1, "source": "yellowjacket", "target": "be"}, {"color": "#aaa", "id": "e156", "size": 0.1, "source": "hornet", "target": "be"}, {"color": "#aaa", "id": "e157", "size": 0.1, "source": "wasp", "target": "be"}, {"color": "#aaa", "id": "e158", "size": 0.1, "source": "bee", "target": "be"}, {"color": "#aaa", "id": "e159", "size": 0.1, "source": "adult", "target": "be"}, {"color": "#aaa", "id": "e160", "size": 0.1, "source": "ant", "target": "be"}, {"color": "#aaa", "id": "e161", "size": 0.1, "source": "most people", "target": "simply avoid"}, {"color": "#aaa", "id": "e162", "size": 0.1, "source": "question", "target": "simply avoid"}, {"color": "#aaa", "id": "e163", "size": 0.1, "source": "-PRON-", "target": "be advise"}, {"color": "#aaa", "id": "e164", "size": 0.1, "source": "most people", "target": "be advise"}, {"color": "#aaa", "id": "e165", "size": 0.1, "source": "question", "target": "be advise"}, {"color": "#aaa", "id": "e166", "size": 0.1, "source": "a medical emergency", "target": "may require"}, {"color": "#aaa", "id": "e167", "size": 0.1, "source": "resuscitation measure", "target": "may require"}, {"color": "#aaa", "id": "e168", "size": 0.1, "source": "close monitoring", "target": "may require"}, {"color": "#aaa", "id": "e169", "size": 0.1, "source": "a medical emergency", "target": "be"}, {"color": "#aaa", "id": "e170", "size": 0.1, "source": "resuscitation measure", "target": "be"}, {"color": "#aaa", "id": "e171", "size": 0.1, "source": "close monitoring", "target": "be"}, {"color": "#aaa", "id": "e172", "size": 0.1, "source": "intravenous fluid", "target": "may require"}, {"color": "#aaa", "id": "e173", "size": 0.1, "source": "large volume", "target": "may require"}, {"color": "#aaa", "id": "e174", "size": 0.1, "source": "large volume", "target": "be"}, {"color": "#aaa", "id": "e175", "size": 0.1, "source": "supplemental oxygen", "target": "may require"}, {"color": "#aaa", "id": "e176", "size": 0.1, "source": "supplemental oxygen", "target": "be"}, {"color": "#aaa", "id": "e177", "size": 0.1, "source": "airway management", "target": "may require"}, {"color": "#aaa", "id": "e178", "size": 0.1, "source": "airway management", "target": "be"}, {"color": "#aaa", "id": "e179", "size": 0.1, "source": "the treatment", "target": "use"}, {"color": "#aaa", "id": "e180", "size": 0.1, "source": "adjunct", "target": "use"}, {"color": "#aaa", "id": "e181", "size": 0.1, "source": "steroid", "target": "use"}, {"color": "#aaa", "id": "e182", "size": 0.1, "source": "choice", "target": "use"}, {"color": "#aaa", "id": "e183", "size": 0.1, "source": "epinephrine", "target": "be"}, {"color": "#aaa", "id": "e184", "size": 0.1, "source": "adjunct", "target": "be"}, {"color": "#aaa", "id": "e185", "size": 0.1, "source": "the treatment", "target": "be"}, {"color": "#aaa", "id": "e186", "size": 0.1, "source": "steroid", "target": "be"}, {"color": "#aaa", "id": "e187", "size": 0.1, "source": "example", "target": "be"}, {"color": "#aaa", "id": "e188", "size": 0.1, "source": "choice", "target": "be"}, {"color": "#aaa", "id": "e189", "size": 0.1, "source": "antihistamine", "target": "use"}, {"color": "#aaa", "id": "e190", "size": 0.1, "source": "example", "target": "use"}, {"color": "#aaa", "id": "e191", "size": 0.1, "source": "dexamethasone", "target": "be"}, {"color": "#aaa", "id": "e192", "size": 0.1, "source": "antihistamine", "target": "be"}, {"color": "#aaa", "id": "e193", "size": 0.1, "source": "a period", "target": "be recommend"}, {"color": "#aaa", "id": "e194", "size": 0.1, "source": "hospital", "target": "be recommend"}, {"color": "#aaa", "id": "e195", "size": 0.1, "source": "24 hour", "target": "be recommend"}, {"color": "#aaa", "id": "e196", "size": 0.1, "source": "between 2", "target": "be recommend"}, {"color": "#aaa", "id": "e197", "size": 0.1, "source": "no absolute contraindication", "target": "be"}, {"color": "#aaa", "id": "e198", "size": 0.1, "source": "-PRON- use", "target": "be"}, {"color": "#aaa", "id": "e199", "size": 0.1, "source": "epinephrine", "target": "include"}, {"color": "#aaa", "id": "e200", "size": 0.1, "source": "palpitation", "target": "include"}, {"color": "#aaa", "id": "e201", "size": 0.1, "source": "headache", "target": "include"}, {"color": "#aaa", "id": "e202", "size": 0.1, "source": "anxiety", "target": "include"}, {"color": "#aaa", "id": "e203", "size": 0.1, "source": "tremor", "target": "include"}, {"color": "#aaa", "id": "e204", "size": 0.1, "source": "people", "target": "may be"}, {"color": "#aaa", "id": "e205", "size": 0.1, "source": "epinephrine", "target": "may be"}, {"color": "#aaa", "id": "e206", "size": 0.1, "source": "the effect", "target": "may be"}, {"color": "#aaa", "id": "e207", "size": 0.1, "source": "\u03b2-blocker", "target": "may be"}, {"color": "#aaa", "id": "e208", "size": 0.1, "source": "epinephrine", "target": "be not"}, {"color": "#aaa", "id": "e209", "size": 0.1, "source": "effective", "target": "be not"}, {"color": "#aaa", "id": "e210", "size": 0.1, "source": "adult", "target": "weigh"}, {"color": "#aaa", "id": "e211", "size": 0.1, "source": "child", "target": "weigh"}, {"color": "#aaa", "id": "e212", "size": 0.1, "source": "corticosteroid", "target": "may be use"}, {"color": "#aaa", "id": "e213", "size": 0.1, "source": "the risk", "target": "may be use"}, {"color": "#aaa", "id": "e214", "size": 0.1, "source": "biphasic anaphylaxis", "target": "may be use"}, {"color": "#aaa", "id": "e215", "size": 0.1, "source": "the hope", "target": "may be use"}, {"color": "#aaa", "id": "e216", "size": 0.1, "source": "corticosteroid", "target": "to make"}, {"color": "#aaa", "id": "e217", "size": 0.1, "source": "anaphylaxis", "target": "to make"}, {"color": "#aaa", "id": "e218", "size": 0.1, "source": "the current episode", "target": "to make"}, {"color": "#aaa", "id": "e219", "size": 0.1, "source": "a difference", "target": "to make"}, {"color": "#aaa", "id": "e220", "size": 0.1, "source": "corticosteroid", "target": "be"}, {"color": "#aaa", "id": "e221", "size": 0.1, "source": "the current episode", "target": "be"}, {"color": "#aaa", "id": "e222", "size": 0.1, "source": "a difference", "target": "be"}, {"color": "#aaa", "id": "e223", "size": 0.1, "source": "people", "target": "to have"}, {"color": "#aaa", "id": "e224", "size": 0.1, "source": "\"an \"\" allergy action plan\"", "target": "to have"}, {"color": "#aaa", "id": "e225", "size": 0.1, "source": "anaphylaxis", "target": "to have"}, {"color": "#aaa", "id": "e226", "size": 0.1, "source": "certain trigger", "target": "be"}, {"color": "#aaa", "id": "e227", "size": 0.1, "source": "oral desensitization", "target": "be"}, {"color": "#aaa", "id": "e228", "size": 0.1, "source": "many food", "target": "be"}, {"color": "#aaa", "id": "e229", "size": 0.1, "source": "case", "target": "cause"}, {"color": "#aaa", "id": "e230", "size": 0.1, "source": "death", "target": "cause"}, {"color": "#aaa", "id": "e231", "size": 0.1, "source": "people", "target": "get"}, {"color": "#aaa", "id": "e232", "size": 0.1, "source": "old", "target": "get"}, {"color": "#aaa", "id": "e233", "size": 0.1, "source": "people", "target": "have a lifetime risk of"}, {"color": "#aaa", "id": "e234", "size": 0.1, "source": "0.05 -2 %", "target": "have a lifetime risk of"}, {"color": "#aaa", "id": "e235", "size": 0.1, "source": "anaphylaxis", "target": "have a lifetime risk of"}, {"color": "#aaa", "id": "e236", "size": 0.1, "source": "the number", "target": "have a lifetime risk of"}, {"color": "#aaa", "id": "e237", "size": 0.1, "source": "who", "target": "have a lifetime risk of"}, {"color": "#aaa", "id": "e238", "size": 0.1, "source": "4", "target": "be"}, {"color": "#aaa", "id": "e239", "size": 0.1, "source": "year", "target": "be"}, {"color": "#aaa", "id": "e240", "size": 0.1, "source": "100000", "target": "be"}, {"color": "#aaa", "id": "e241", "size": 0.1, "source": "100000 person", "target": "be"}, {"color": "#aaa", "id": "e242", "size": 0.1, "source": "the number", "target": "be"}, {"color": "#aaa", "id": "e243", "size": 0.1, "source": "who", "target": "be"}, {"color": "#aaa", "id": "e244", "size": 0.1, "source": "4 - 100", "target": "be"}, {"color": "#aaa", "id": "e245", "size": 0.1, "source": "\"4 - 100 per 100", "target": "be"}, {"color": "#aaa", "id": "e246", "size": 0.1, "source": "anaphylaxis", "target": "get"}, {"color": "#aaa", "id": "e247", "size": 0.1, "source": "more than one", "target": "get"}, {"color": "#aaa", "id": "e248", "size": 0.1, "source": "more than one attack", "target": "get"}, {"color": "#aaa", "id": "e249", "size": 0.1, "source": "-PRON-", "target": "be"}, {"color": "#aaa", "id": "e250", "size": 0.1, "source": "the 1980s", "target": "be"}, {"color": "#aaa", "id": "e251", "size": 0.1, "source": "anaphylaxis", "target": "lead"}, {"color": "#aaa", "id": "e252", "size": 0.1, "source": "year", "target": "lead"}, {"color": "#aaa", "id": "e253", "size": 0.1, "source": "000", "target": "lead"}, {"color": "#aaa", "id": "e254", "size": 0.1, "source": "2.4", "target": "lead"}, {"color": "#aaa", "id": "e255", "size": 0.1, "source": "\"500 - 1 ", "target": "lead"}, {"color": "#aaa", "id": "e256", "size": 0.1, "source": "15 death", "target": "lead"}, {"color": "#aaa", "id": "e257", "size": 0.1, "source": "500", "target": "lead"}, {"color": "#aaa", "id": "e258", "size": 0.1, "source": "australia", "target": "lead"}, {"color": "#aaa", "id": "e259", "size": 0.1, "source": "15", "target": "lead"}, {"color": "#aaa", "id": "e260", "size": 0.1, "source": "the united states", "target": "lead"}, {"color": "#aaa", "id": "e261", "size": 0.1, "source": "death", "target": "primarily occur"}, {"color": "#aaa", "id": "e262", "size": 0.1, "source": "male", "target": "primarily occur"}, {"color": "#aaa", "id": "e263", "size": 0.1, "source": "death", "target": "be most commonly trigger"}, {"color": "#aaa", "id": "e264", "size": 0.1, "source": "medication", "target": "be most commonly trigger"}, {"color": "#aaa", "id": "e265", "size": 0.1, "source": "anaphylaxis", "target": "be most commonly trigger"}, {"color": "#aaa", "id": "e266", "size": 0.1, "source": "the term", "target": "change"}, {"color": "#aaa", "id": "e267", "size": 0.1, "source": "anaphylaxis", "target": "change"}, {"color": "#aaa", "id": "e268", "size": 0.1, "source": "speech", "target": "change"}, {"color": "#aaa", "id": "e269", "size": 0.1, "source": "-PRON- nice quality", "target": "change"}]}