{"nodes": [{"color": "#f00", "id": "italian", "size": 9, "label": "italian", "x": 9, "y": 115}, {"color": "#00f", "id": "play", "size": 9, "label": "play", "x": 250, "y": 186}, {"color": "#f00", "id": "the italian national team", "size": 9, "label": "the italian national team", "x": 0, "y": -32}, {"color": "#f00", "id": "an italian professional footballer", "size": 9, "label": "an italian professional footballer", "x": 9, "y": 115}, {"color": "#f00", "id": "2", "size": 9, "label": "2", "x": 9, "y": 115}, {"color": "#00f", "id": "be", "size": 9, "label": "be", "x": 250, "y": 186}, {"color": "#f00", "id": "who", "size": 9, "label": "who", "x": 0, "y": -32}, {"color": "#f00", "id": "january 1991", "size": 9, "label": "january 1991", "x": 9, "y": 115}, {"color": "#00ff7f", "id": "davide santon", "size": 9, "label": "davide santon", "x": 9, "y": 115}, {"color": "#f00", "id": "italian club", "size": 9, "label": "italian club", "x": 0, "y": -32}, {"color": "#f00", "id": "internazionale", "size": 9, "label": "internazionale", "x": 0, "y": -32}, {"color": "#f00", "id": "italian club internazionale", "size": 9, "label": "italian club internazionale", "x": 0, "y": -32}, {"color": "#f00", "id": "-PRON-", "size": 9, "label": "-PRON-", "x": 9, "y": 115}, {"color": "#00f", "id": "start -PRON- career revert", "size": 9, "label": "start -PRON- career revert", "x": 250, "y": 186}, {"color": "#f00", "id": "an attacking", "size": 9, "label": "an attacking", "x": 0, "y": -32}, {"color": "#00f", "id": "start", "size": 9, "label": "start", "x": 250, "y": 186}, {"color": "#f00", "id": "-PRON- career", "size": 9, "label": "-PRON- career", "x": 0, "y": -32}, {"color": "#00f", "id": "be know", "size": 9, "label": "be know", "x": 250, "y": 186}, {"color": "#f00", "id": "the flank", "size": 9, "label": "the flank", "x": 0, "y": -32}, {"color": "#f00", "id": "\"-PRON- pacy ", "size": 9, "label": "\"-PRON- pacy ", "x": 0, "y": -32}, {"color": "#f00", "id": "2009", "size": 9, "label": "2009", "x": 9, "y": 115}, {"color": "#00f", "id": "lead -PRON- coach also compare", "size": 9, "label": "lead -PRON- coach also compare", "x": 250, "y": 186}, {"color": "#f00", "id": "-PRON- precocious display", "size": 9, "label": "-PRON- precocious display", "x": 9, "y": 115}, {"color": "#008000", "id": "italy", "size": 9, "label": "italy", "x": 9, "y": 115}, {"color": "#00f", "id": "lead", "size": 9, "label": "lead", "x": 250, "y": 186}, {"color": "#f00", "id": "-PRON- coach", "size": 9, "label": "-PRON- coach", "x": 0, "y": -32}, {"color": "#f00", "id": "marcello lippi", "size": 9, "label": "marcello lippi", "x": 9, "y": 115}, {"color": "#00f", "id": "to describe", "size": 9, "label": "to describe", "x": 250, "y": 186}, {"color": "#f00", "id": "inter", "size": 9, "label": "inter", "x": 9, "y": 115}, {"color": "#f00", "id": "jos\u00e9 mourinho", "size": 9, "label": "jos\u00e9 mourinho", "x": 9, "y": 115}, {"color": "#00f", "id": "be include", "size": 9, "label": "be include", "x": 250, "y": 186}, {"color": "#f00", "id": "the world", "size": 9, "label": "the world", "x": 0, "y": -32}, {"color": "#f00", "id": "the don bal\u00f3n list", "size": 9, "label": "the don bal\u00f3n list", "x": 0, "y": -32}, {"color": "#f00", "id": "the good young footballer", "size": 9, "label": "the good young footballer", "x": 0, "y": -32}, {"color": "#f00", "id": "don bal\u00f3n", "size": 9, "label": "don bal\u00f3n", "x": 0, "y": -32}, {"color": "#00f", "id": "before move", "size": 9, "label": "before move", "x": 250, "y": 186}, {"color": "#f00", "id": "a defensive role", "size": 9, "label": "a defensive role", "x": 0, "y": -32}, {"color": "#00f", "id": "start out", "size": 9, "label": "start out", "x": 250, "y": 186}, {"color": "#f00", "id": "a winger", "size": 9, "label": "a winger", "x": 0, "y": -32}, {"color": "#00f", "id": "be call up", "size": 9, "label": "be call up", "x": 250, "y": 186}, {"color": "#f00", "id": "the first half of the season", "size": 9, "label": "the first half of the season", "x": 0, "y": -32}, {"color": "#f00", "id": "the first team", "size": 9, "label": "the first team", "x": 0, "y": -32}, {"color": "#f00", "id": "the training session", "size": 9, "label": "the training session", "x": 0, "y": -32}, {"color": "#f00", "id": "the first half", "size": 9, "label": "the first half", "x": 0, "y": -32}, {"color": "#f00", "id": "the season", "size": 9, "label": "the season", "x": 0, "y": -32}, {"color": "#f00", "id": "2008 - 09", "size": 9, "label": "2008 - 09", "x": 0, "y": -32}, {"color": "#f00", "id": "pre - season", "size": 9, "label": "pre - season", "x": 0, "y": -32}, {"color": "#f00", "id": "south tyrol", "size": 9, "label": "south tyrol", "x": 0, "y": -32}, {"color": "#f00", "id": "the 2008 - 09 pre - season training", "size": 9, "label": "the 2008 - 09 pre - season training", "x": 0, "y": -32}, {"color": "#00f", "id": "to join", "size": 9, "label": "to join", "x": 250, "y": 186}, {"color": "#f00", "id": "first", "size": 9, "label": "first", "x": 0, "y": -32}, {"color": "#00f", "id": "name", "size": 9, "label": "name", "x": 250, "y": 186}, {"color": "#f00", "id": "santon", "size": 9, "label": "santon", "x": 0, "y": -32}, {"color": "#f00", "id": "jos\u00e9", "size": 9, "label": "jos\u00e9", "x": 9, "y": 115}, {"color": "#00f", "id": "do not use", "size": 9, "label": "do not use", "x": 250, "y": 186}, {"color": "#00f", "id": "make", "size": 9, "label": "make", "x": 250, "y": 186}, {"color": "#f00", "id": "-PRON- debut", "size": 9, "label": "-PRON- debut", "x": 0, "y": -32}, {"color": "#f00", "id": "serie a", "size": 9, "label": "serie a", "x": 0, "y": -32}, {"color": "#f00", "id": "-PRON- serie a debut", "size": 9, "label": "-PRON- serie a debut", "x": 0, "y": -32}, {"color": "#f00", "id": "european", "size": 9, "label": "european", "x": 0, "y": -32}, {"color": "#f00", "id": "-PRON- european debut", "size": 9, "label": "-PRON- european debut", "x": 0, "y": -32}, {"color": "#00f", "id": "garner", "size": 9, "label": "garner", "x": 250, "y": 186}, {"color": "#f00", "id": "praise", "size": 9, "label": "praise", "x": 0, "y": -32}, {"color": "#f00", "id": "a great footballer", "size": 9, "label": "a great footballer", "x": 0, "y": -32}, {"color": "#f00", "id": "a really interesting lad", "size": 9, "label": "a really interesting lad", "x": 0, "y": -32}, {"color": "#00f", "id": "make thus win", "size": 9, "label": "make thus win", "x": 250, "y": 186}, {"color": "#f00", "id": "-PRON- first senior honour", "size": 9, "label": "-PRON- first senior honour", "x": 0, "y": -32}, {"color": "#f00", "id": "two substitute appearance", "size": 9, "label": "two substitute appearance", "x": 0, "y": -32}, {"color": "#f00", "id": "two", "size": 9, "label": "two", "x": 0, "y": -32}, {"color": "#00f", "id": "start 13 league game thus win", "size": 9, "label": "start 13 league game thus win", "x": 250, "y": 186}, {"color": "#f00", "id": "13", "size": 9, "label": "13", "x": 0, "y": -32}, {"color": "#f00", "id": "13 league game", "size": 9, "label": "13 league game", "x": 0, "y": -32}, {"color": "#00f", "id": "[ be ] former head coach [ from ]", "size": 9, "label": "[ be ] former head coach [ from ]", "x": 250, "y": 186}, {"color": "#f00", "id": "a predestined player", "size": 9, "label": "a predestined player", "x": 9, "y": 115}, {"color": "#00f", "id": "remind", "size": 9, "label": "remind", "x": 250, "y": 186}, {"color": "#00f", "id": "have also become", "size": 9, "label": "have also become", "x": 250, "y": 186}, {"color": "#f00", "id": "subject", "size": 9, "label": "subject", "x": 0, "y": -32}, {"color": "#f00", "id": "former italy head coach marcello lippi", "size": 9, "label": "former italy head coach marcello lippi", "x": 0, "y": -32}, {"color": "#00f", "id": "after sustain", "size": 9, "label": "after sustain", "x": 250, "y": 186}, {"color": "#f00", "id": "a right knee", "size": 9, "label": "a right knee", "x": 0, "y": -32}, {"color": "#f00", "id": "out", "size": 9, "label": "out", "x": 0, "y": -32}, {"color": "#00f", "id": "be call", "size": 9, "label": "be call", "x": 250, "y": 186}, {"color": "#f00", "id": "back", "size": 9, "label": "back", "x": 0, "y": -32}, {"color": "#f00", "id": "-PRON- return", "size": 9, "label": "-PRON- return", "x": 0, "y": -32}, {"color": "#00f", "id": "require", "size": 9, "label": "require", "x": 250, "y": 186}, {"color": "#f00", "id": "surgery", "size": 9, "label": "surgery", "x": 0, "y": -32}, {"color": "#00f", "id": "after return", "size": 9, "label": "after return", "x": 250, "y": 186}, {"color": "#f00", "id": "the previous injury", "size": 9, "label": "the previous injury", "x": 0, "y": -32}, {"color": "#00f", "id": "injure", "size": 9, "label": "injure", "x": 250, "y": 186}, {"color": "#f00", "id": "the same knee", "size": 9, "label": "the same knee", "x": 0, "y": -32}, {"color": "#f00", "id": "the injury crisis", "size": 9, "label": "the injury crisis", "x": 0, "y": -32}, {"color": "#00f", "id": "be send", "size": 9, "label": "be send", "x": 250, "y": 186}, {"color": "#00f", "id": "return", "size": 9, "label": "return", "x": 250, "y": 186}, {"color": "#f00", "id": "the club", "size": 9, "label": "the club", "x": 9, "y": 115}, {"color": "#00f", "id": "sell", "size": 9, "label": "sell", "x": 250, "y": 186}, {"color": "#f00", "id": "newcastle", "size": 9, "label": "newcastle", "x": 0, "y": -32}, {"color": "#f00", "id": "-PRON- newcastle debut", "size": 9, "label": "-PRON- newcastle debut", "x": 0, "y": -32}, {"color": "#00f", "id": "go on to make away", "size": 9, "label": "go on to make away", "x": 250, "y": 186}, {"color": "#f00", "id": "-PRON- first league", "size": 9, "label": "-PRON- first league", "x": 0, "y": -32}, {"color": "#f00", "id": "december", "size": 9, "label": "december", "x": 0, "y": -32}, {"color": "#00f", "id": "go on", "size": 9, "label": "go on", "x": 250, "y": 186}, {"color": "#f00", "id": "norwich city", "size": 9, "label": "norwich city", "x": 0, "y": -32}, {"color": "#00f", "id": "set up", "size": 9, "label": "set up", "x": 250, "y": 186}, {"color": "#f00", "id": "ciss\u00e9", "size": 9, "label": "ciss\u00e9", "x": 0, "y": -32}, {"color": "#f00", "id": "papiss ciss\u00e9 's first goal\"]", "size": 9, "label": "papiss ciss\u00e9 's first goal\"]", "x": 0, "y": -32}, {"color": "#f00", "id": "the magpies shock", "size": 9, "label": "the magpies shock", "x": 0, "y": -32}, {"color": "#00f", "id": "assist", "size": 9, "label": "assist", "x": 250, "y": 186}, {"color": "#f00", "id": "the first goal", "size": 9, "label": "the first goal", "x": 0, "y": -32}, {"color": "#f00", "id": "a cross", "size": 9, "label": "a cross", "x": 0, "y": -32}, {"color": "#f00", "id": "the win goal", "size": 9, "label": "the win goal", "x": 0, "y": -32}, {"color": "#f00", "id": "jon\u00e1s guti\u00e9rrez", "size": 9, "label": "jon\u00e1s guti\u00e9rrez", "x": 0, "y": -32}, {"color": "#00f", "id": "score", "size": 9, "label": "score", "x": 250, "y": 186}, {"color": "#f00", "id": "-PRON- first goal", "size": 9, "label": "-PRON- first goal", "x": 0, "y": -32}, {"color": "#00f", "id": "make play", "size": 9, "label": "make play", "x": 250, "y": 186}, {"color": "#f00", "id": "parkstad limburg stadion", "size": 9, "label": "parkstad limburg stadion", "x": 0, "y": -32}, {"color": "#00f", "id": "end", "size": 9, "label": "end", "x": 250, "y": 186}, {"color": "#f00", "id": "1", "size": 9, "label": "1", "x": 0, "y": -32}, {"color": "#f00", "id": "a 1 - 1 draw", "size": 9, "label": "a 1 - 1 draw", "x": 0, "y": -32}, {"color": "#00f", "id": "play -PRON- solid performance earn", "size": 9, "label": "play -PRON- solid performance earn", "x": 250, "y": 186}, {"color": "#f00", "id": "-PRON- solid performance", "size": 9, "label": "-PRON- solid performance", "x": 0, "y": -32}, {"color": "#00f", "id": "play the whole match earn", "size": 9, "label": "play the whole match earn", "x": 250, "y": 186}, {"color": "#f00", "id": "the whole match", "size": 9, "label": "the whole match", "x": 0, "y": -32}, {"color": "#f00", "id": "lippi", "size": 9, "label": "lippi", "x": 9, "y": 115}, {"color": "#00f", "id": "to name", "size": 9, "label": "to name", "x": 250, "y": 186}, {"color": "#00f", "id": "start the next game earn", "size": 9, "label": "start the next game earn", "x": 250, "y": 186}, {"color": "#f00", "id": "eighth", "size": 9, "label": "eighth", "x": 0, "y": -32}, {"color": "#f00", "id": "netherlands", "size": 9, "label": "netherlands", "x": 0, "y": -32}, {"color": "#f00", "id": "the netherlands", "size": 9, "label": "the netherlands", "x": 0, "y": -32}, {"color": "#f00", "id": "6 february 2013", "size": 9, "label": "6 february 2013", "x": 0, "y": -32}, {"color": "#f00", "id": "-PRON- eighth national cap", "size": 9, "label": "-PRON- eighth national cap", "x": 0, "y": -32}, {"color": "#f00", "id": "6 february", "size": 9, "label": "6 february", "x": 0, "y": -32}, {"color": "#f00", "id": "amsterdam", "size": 9, "label": "amsterdam", "x": 0, "y": -32}, {"color": "#f00", "id": "the next game", "size": 9, "label": "the next game", "x": 0, "y": -32}, {"color": "#00f", "id": "give", "size": 9, "label": "give", "x": 250, "y": 186}, {"color": "#f00", "id": "birth", "size": 9, "label": "birth", "x": 0, "y": -32}], "edges": [{"color": "#aaa", "id": "e1", "size": 0.1, "source": "italian", "target": "play"}, {"color": "#aaa", "id": "e2", "size": 0.1, "source": "the italian national team", "target": "play"}, {"color": "#aaa", "id": "e3", "size": 0.1, "source": "an italian professional footballer", "target": "play"}, {"color": "#aaa", "id": "e4", "size": 0.1, "source": "2", "target": "be"}, {"color": "#aaa", "id": "e5", "size": 0.1, "source": "the italian national team", "target": "be"}, {"color": "#aaa", "id": "e6", "size": 0.1, "source": "an italian professional footballer", "target": "be"}, {"color": "#aaa", "id": "e7", "size": 0.1, "source": "italian", "target": "be"}, {"color": "#aaa", "id": "e8", "size": 0.1, "source": "who", "target": "be"}, {"color": "#aaa", "id": "e9", "size": 0.1, "source": "january 1991", "target": "be"}, {"color": "#aaa", "id": "e10", "size": 0.1, "source": "davide santon", "target": "be"}, {"color": "#aaa", "id": "e11", "size": 0.1, "source": "italian club", "target": "play"}, {"color": "#aaa", "id": "e12", "size": 0.1, "source": "internazionale", "target": "play"}, {"color": "#aaa", "id": "e13", "size": 0.1, "source": "italian club internazionale", "target": "be"}, {"color": "#aaa", "id": "e14", "size": 0.1, "source": "-PRON-", "target": "start -PRON- career revert"}, {"color": "#aaa", "id": "e15", "size": 0.1, "source": "an attacking", "target": "start -PRON- career revert"}, {"color": "#aaa", "id": "e16", "size": 0.1, "source": "-PRON-", "target": "start"}, {"color": "#aaa", "id": "e17", "size": 0.1, "source": "-PRON- career", "target": "start"}, {"color": "#aaa", "id": "e18", "size": 0.1, "source": "-PRON-", "target": "be know"}, {"color": "#aaa", "id": "e19", "size": 0.1, "source": "the flank", "target": "be know"}, {"color": "#aaa", "id": "e20", "size": 0.1, "source": "\"-PRON- pacy ", "target": "be know"}, {"color": "#aaa", "id": "e21", "size": 0.1, "source": "2009", "target": "lead -PRON- coach also compare"}, {"color": "#aaa", "id": "e22", "size": 0.1, "source": "-PRON-", "target": "lead -PRON- coach also compare"}, {"color": "#aaa", "id": "e23", "size": 0.1, "source": "-PRON- precocious display", "target": "lead -PRON- coach also compare"}, {"color": "#aaa", "id": "e24", "size": 0.1, "source": "italy", "target": "lead -PRON- coach also compare"}, {"color": "#aaa", "id": "e25", "size": 0.1, "source": "2009", "target": "lead"}, {"color": "#aaa", "id": "e26", "size": 0.1, "source": "-PRON- coach", "target": "lead"}, {"color": "#aaa", "id": "e27", "size": 0.1, "source": "-PRON- precocious display", "target": "lead"}, {"color": "#aaa", "id": "e28", "size": 0.1, "source": "italy", "target": "lead"}, {"color": "#aaa", "id": "e29", "size": 0.1, "source": "marcello lippi", "target": "to describe"}, {"color": "#aaa", "id": "e30", "size": 0.1, "source": "-PRON-", "target": "to describe"}, {"color": "#aaa", "id": "e31", "size": 0.1, "source": "inter", "target": "lead -PRON- coach also compare"}, {"color": "#aaa", "id": "e32", "size": 0.1, "source": "inter", "target": "lead"}, {"color": "#aaa", "id": "e33", "size": 0.1, "source": "jos\u00e9 mourinho", "target": "to describe"}, {"color": "#aaa", "id": "e34", "size": 0.1, "source": "-PRON-", "target": "be include"}, {"color": "#aaa", "id": "e35", "size": 0.1, "source": "the world", "target": "be include"}, {"color": "#aaa", "id": "e36", "size": 0.1, "source": "the don bal\u00f3n list", "target": "be include"}, {"color": "#aaa", "id": "e37", "size": 0.1, "source": "the good young footballer", "target": "be include"}, {"color": "#aaa", "id": "e38", "size": 0.1, "source": "don bal\u00f3n", "target": "be include"}, {"color": "#aaa", "id": "e39", "size": 0.1, "source": "-PRON-", "target": "before move"}, {"color": "#aaa", "id": "e40", "size": 0.1, "source": "a defensive role", "target": "before move"}, {"color": "#aaa", "id": "e41", "size": 0.1, "source": "-PRON-", "target": "start out"}, {"color": "#aaa", "id": "e42", "size": 0.1, "source": "a winger", "target": "start out"}, {"color": "#aaa", "id": "e43", "size": 0.1, "source": "-PRON-", "target": "be call up"}, {"color": "#aaa", "id": "e44", "size": 0.1, "source": "the first half of the season", "target": "be call up"}, {"color": "#aaa", "id": "e45", "size": 0.1, "source": "the first team", "target": "be call up"}, {"color": "#aaa", "id": "e46", "size": 0.1, "source": "the training session", "target": "be call up"}, {"color": "#aaa", "id": "e47", "size": 0.1, "source": "the first half", "target": "be call up"}, {"color": "#aaa", "id": "e48", "size": 0.1, "source": "the season", "target": "be call up"}, {"color": "#aaa", "id": "e49", "size": 0.1, "source": "2008 - 09", "target": "be call up"}, {"color": "#aaa", "id": "e50", "size": 0.1, "source": "pre - season", "target": "be call up"}, {"color": "#aaa", "id": "e51", "size": 0.1, "source": "south tyrol", "target": "be call up"}, {"color": "#aaa", "id": "e52", "size": 0.1, "source": "the 2008 - 09 pre - season training", "target": "be call up"}, {"color": "#aaa", "id": "e53", "size": 0.1, "source": "-PRON-", "target": "to join"}, {"color": "#aaa", "id": "e54", "size": 0.1, "source": "the first team", "target": "to join"}, {"color": "#aaa", "id": "e55", "size": 0.1, "source": "the training session", "target": "to join"}, {"color": "#aaa", "id": "e56", "size": 0.1, "source": "first", "target": "to join"}, {"color": "#aaa", "id": "e57", "size": 0.1, "source": "2008 - 09", "target": "to join"}, {"color": "#aaa", "id": "e58", "size": 0.1, "source": "pre - season", "target": "to join"}, {"color": "#aaa", "id": "e59", "size": 0.1, "source": "south tyrol", "target": "to join"}, {"color": "#aaa", "id": "e60", "size": 0.1, "source": "the 2008 - 09 pre - season training", "target": "to join"}, {"color": "#aaa", "id": "e61", "size": 0.1, "source": "jos\u00e9 mourinho", "target": "name"}, {"color": "#aaa", "id": "e62", "size": 0.1, "source": "santon", "target": "name"}, {"color": "#aaa", "id": "e63", "size": 0.1, "source": "jos\u00e9", "target": "do not use"}, {"color": "#aaa", "id": "e64", "size": 0.1, "source": "-PRON-", "target": "do not use"}, {"color": "#aaa", "id": "e65", "size": 0.1, "source": "santon", "target": "make"}, {"color": "#aaa", "id": "e66", "size": 0.1, "source": "-PRON- debut", "target": "make"}, {"color": "#aaa", "id": "e67", "size": 0.1, "source": "-PRON-", "target": "make"}, {"color": "#aaa", "id": "e68", "size": 0.1, "source": "serie a", "target": "make"}, {"color": "#aaa", "id": "e69", "size": 0.1, "source": "-PRON- serie a debut", "target": "make"}, {"color": "#aaa", "id": "e70", "size": 0.1, "source": "european", "target": "make"}, {"color": "#aaa", "id": "e71", "size": 0.1, "source": "-PRON- european debut", "target": "make"}, {"color": "#aaa", "id": "e72", "size": 0.1, "source": "santon", "target": "garner"}, {"color": "#aaa", "id": "e73", "size": 0.1, "source": "praise", "target": "garner"}, {"color": "#aaa", "id": "e74", "size": 0.1, "source": "-PRON-", "target": "be"}, {"color": "#aaa", "id": "e75", "size": 0.1, "source": "santon", "target": "be"}, {"color": "#aaa", "id": "e76", "size": 0.1, "source": "a great footballer", "target": "be"}, {"color": "#aaa", "id": "e77", "size": 0.1, "source": "a really interesting lad", "target": "be"}, {"color": "#aaa", "id": "e78", "size": 0.1, "source": "-PRON-", "target": "make thus win"}, {"color": "#aaa", "id": "e79", "size": 0.1, "source": "-PRON- first senior honour", "target": "make thus win"}, {"color": "#aaa", "id": "e80", "size": 0.1, "source": "first", "target": "make thus win"}, {"color": "#aaa", "id": "e81", "size": 0.1, "source": "two substitute appearance", "target": "make"}, {"color": "#aaa", "id": "e82", "size": 0.1, "source": "two", "target": "make"}, {"color": "#aaa", "id": "e83", "size": 0.1, "source": "-PRON-", "target": "start 13 league game thus win"}, {"color": "#aaa", "id": "e84", "size": 0.1, "source": "-PRON- first senior honour", "target": "start 13 league game thus win"}, {"color": "#aaa", "id": "e85", "size": 0.1, "source": "first", "target": "start 13 league game thus win"}, {"color": "#aaa", "id": "e86", "size": 0.1, "source": "13", "target": "start"}, {"color": "#aaa", "id": "e87", "size": 0.1, "source": "13 league game", "target": "start"}, {"color": "#aaa", "id": "e88", "size": 0.1, "source": "marcello lippi", "target": "[ be ] former head coach [ from ]"}, {"color": "#aaa", "id": "e89", "size": 0.1, "source": "italy", "target": "[ be ] former head coach [ from ]"}, {"color": "#aaa", "id": "e90", "size": 0.1, "source": "a predestined player", "target": "remind"}, {"color": "#aaa", "id": "e91", "size": 0.1, "source": "-PRON-", "target": "remind"}, {"color": "#aaa", "id": "e92", "size": 0.1, "source": "-PRON-", "target": "have also become"}, {"color": "#aaa", "id": "e93", "size": 0.1, "source": "praise", "target": "have also become"}, {"color": "#aaa", "id": "e94", "size": 0.1, "source": "italy", "target": "have also become"}, {"color": "#aaa", "id": "e95", "size": 0.1, "source": "marcello lippi", "target": "have also become"}, {"color": "#aaa", "id": "e96", "size": 0.1, "source": "subject", "target": "have also become"}, {"color": "#aaa", "id": "e97", "size": 0.1, "source": "former italy head coach marcello lippi", "target": "have also become"}, {"color": "#aaa", "id": "e98", "size": 0.1, "source": "2009", "target": "have also become"}, {"color": "#aaa", "id": "e99", "size": 0.1, "source": "inter", "target": "make"}, {"color": "#aaa", "id": "e100", "size": 0.1, "source": "the season", "target": "make"}, {"color": "#aaa", "id": "e101", "size": 0.1, "source": "first", "target": "make"}, {"color": "#aaa", "id": "e102", "size": 0.1, "source": "-PRON-", "target": "after sustain"}, {"color": "#aaa", "id": "e103", "size": 0.1, "source": "a right knee", "target": "after sustain"}, {"color": "#aaa", "id": "e104", "size": 0.1, "source": "out", "target": "be"}, {"color": "#aaa", "id": "e105", "size": 0.1, "source": "-PRON-", "target": "be call"}, {"color": "#aaa", "id": "e106", "size": 0.1, "source": "back", "target": "be call"}, {"color": "#aaa", "id": "e107", "size": 0.1, "source": "-PRON- return", "target": "make"}, {"color": "#aaa", "id": "e108", "size": 0.1, "source": "-PRON-", "target": "require"}, {"color": "#aaa", "id": "e109", "size": 0.1, "source": "surgery", "target": "require"}, {"color": "#aaa", "id": "e110", "size": 0.1, "source": "-PRON-", "target": "after return"}, {"color": "#aaa", "id": "e111", "size": 0.1, "source": "the previous injury", "target": "after return"}, {"color": "#aaa", "id": "e112", "size": 0.1, "source": "-PRON-", "target": "injure"}, {"color": "#aaa", "id": "e113", "size": 0.1, "source": "the same knee", "target": "injure"}, {"color": "#aaa", "id": "e114", "size": 0.1, "source": "-PRON-", "target": "play"}, {"color": "#aaa", "id": "e115", "size": 0.1, "source": "inter", "target": "play"}, {"color": "#aaa", "id": "e116", "size": 0.1, "source": "the injury crisis", "target": "play"}, {"color": "#aaa", "id": "e117", "size": 0.1, "source": "santon", "target": "be send"}, {"color": "#aaa", "id": "e118", "size": 0.1, "source": "out", "target": "be send"}, {"color": "#aaa", "id": "e119", "size": 0.1, "source": "santon", "target": "return"}, {"color": "#aaa", "id": "e120", "size": 0.1, "source": "inter", "target": "return"}, {"color": "#aaa", "id": "e121", "size": 0.1, "source": "the club", "target": "sell"}, {"color": "#aaa", "id": "e122", "size": 0.1, "source": "santon", "target": "sell"}, {"color": "#aaa", "id": "e123", "size": 0.1, "source": "newcastle", "target": "make"}, {"color": "#aaa", "id": "e124", "size": 0.1, "source": "-PRON- newcastle debut", "target": "make"}, {"color": "#aaa", "id": "e125", "size": 0.1, "source": "-PRON-", "target": "go on to make away"}, {"color": "#aaa", "id": "e126", "size": 0.1, "source": "the club", "target": "go on to make away"}, {"color": "#aaa", "id": "e127", "size": 0.1, "source": "-PRON- first league", "target": "go on to make away"}, {"color": "#aaa", "id": "e128", "size": 0.1, "source": "first", "target": "go on to make away"}, {"color": "#aaa", "id": "e129", "size": 0.1, "source": "december", "target": "go on to make away"}, {"color": "#aaa", "id": "e130", "size": 0.1, "source": "-PRON-", "target": "go on"}, {"color": "#aaa", "id": "e131", "size": 0.1, "source": "-PRON- first league", "target": "go on"}, {"color": "#aaa", "id": "e132", "size": 0.1, "source": "norwich city", "target": "go on"}, {"color": "#aaa", "id": "e133", "size": 0.1, "source": "december", "target": "go on"}, {"color": "#aaa", "id": "e134", "size": 0.1, "source": "the club", "target": "go on"}, {"color": "#aaa", "id": "e135", "size": 0.1, "source": "first", "target": "go on"}, {"color": "#aaa", "id": "e136", "size": 0.1, "source": "-PRON-", "target": "set up"}, {"color": "#aaa", "id": "e137", "size": 0.1, "source": "ciss\u00e9", "target": "set up"}, {"color": "#aaa", "id": "e138", "size": 0.1, "source": "papiss ciss\u00e9 's first goal\"]", "target": "set up"}, {"color": "#aaa", "id": "e139", "size": 0.1, "source": "the magpies shock", "target": "set up"}, {"color": "#aaa", "id": "e140", "size": 0.1, "source": "first", "target": "set up"}, {"color": "#aaa", "id": "e141", "size": 0.1, "source": "newcastle", "target": "be"}, {"color": "#aaa", "id": "e142", "size": 0.1, "source": "-PRON-", "target": "assist"}, {"color": "#aaa", "id": "e143", "size": 0.1, "source": "the first goal", "target": "assist"}, {"color": "#aaa", "id": "e144", "size": 0.1, "source": "a cross", "target": "assist"}, {"color": "#aaa", "id": "e145", "size": 0.1, "source": "first", "target": "assist"}, {"color": "#aaa", "id": "e146", "size": 0.1, "source": "the win goal", "target": "assist"}, {"color": "#aaa", "id": "e147", "size": 0.1, "source": "jon\u00e1s guti\u00e9rrez", "target": "assist"}, {"color": "#aaa", "id": "e148", "size": 0.1, "source": "-PRON-", "target": "score"}, {"color": "#aaa", "id": "e149", "size": 0.1, "source": "-PRON- first goal", "target": "score"}, {"color": "#aaa", "id": "e150", "size": 0.1, "source": "first", "target": "score"}, {"color": "#aaa", "id": "e151", "size": 0.1, "source": "newcastle", "target": "score"}, {"color": "#aaa", "id": "e152", "size": 0.1, "source": "-PRON-", "target": "make play"}, {"color": "#aaa", "id": "e153", "size": 0.1, "source": "parkstad limburg stadion", "target": "make play"}, {"color": "#aaa", "id": "e154", "size": 0.1, "source": "parkstad limburg stadion", "target": "end"}, {"color": "#aaa", "id": "e155", "size": 0.1, "source": "1", "target": "end"}, {"color": "#aaa", "id": "e156", "size": 0.1, "source": "a 1 - 1 draw", "target": "end"}, {"color": "#aaa", "id": "e157", "size": 0.1, "source": "-PRON-", "target": "play -PRON- solid performance earn"}, {"color": "#aaa", "id": "e158", "size": 0.1, "source": "-PRON- solid performance", "target": "play"}, {"color": "#aaa", "id": "e159", "size": 0.1, "source": "-PRON-", "target": "play the whole match earn"}, {"color": "#aaa", "id": "e160", "size": 0.1, "source": "the whole match", "target": "play"}, {"color": "#aaa", "id": "e161", "size": 0.1, "source": "lippi", "target": "to name"}, {"color": "#aaa", "id": "e162", "size": 0.1, "source": "-PRON-", "target": "to name"}, {"color": "#aaa", "id": "e163", "size": 0.1, "source": "lippi", "target": "be"}, {"color": "#aaa", "id": "e164", "size": 0.1, "source": "2009", "target": "be"}, {"color": "#aaa", "id": "e165", "size": 0.1, "source": "-PRON-", "target": "start the next game earn"}, {"color": "#aaa", "id": "e166", "size": 0.1, "source": "eighth", "target": "start the next game earn"}, {"color": "#aaa", "id": "e167", "size": 0.1, "source": "netherlands", "target": "start the next game earn"}, {"color": "#aaa", "id": "e168", "size": 0.1, "source": "the netherlands", "target": "start the next game earn"}, {"color": "#aaa", "id": "e169", "size": 0.1, "source": "a 1 - 1 draw", "target": "start the next game earn"}, {"color": "#aaa", "id": "e170", "size": 0.1, "source": "6 february 2013", "target": "start the next game earn"}, {"color": "#aaa", "id": "e171", "size": 0.1, "source": "-PRON- eighth national cap", "target": "start the next game earn"}, {"color": "#aaa", "id": "e172", "size": 0.1, "source": "1", "target": "start the next game earn"}, {"color": "#aaa", "id": "e173", "size": 0.1, "source": "6 february", "target": "start the next game earn"}, {"color": "#aaa", "id": "e174", "size": 0.1, "source": "amsterdam", "target": "start the next game earn"}, {"color": "#aaa", "id": "e175", "size": 0.1, "source": "the next game", "target": "start"}, {"color": "#aaa", "id": "e176", "size": 0.1, "source": "-PRON-", "target": "give"}, {"color": "#aaa", "id": "e177", "size": 0.1, "source": "birth", "target": "give"}]}